kubernetes_secrets_keyring/__init__.py
kubernetes_secrets_keyring/k8s_keyring_backend.py
kubernetes_secrets_keyring-0.2.5.dist-info/METADATA
kubernetes_secrets_keyring-0.2.5.dist-info/WHEEL
kubernetes_secrets_keyring-0.2.5.dist-info/entry_points.txt
kubernetes_secrets_keyring-0.2.5.dist-info/top_level.txt
kubernetes_secrets_keyring-0.2.5.dist-info/RECORD
