Metadata-Version: 2.1
Name: kubernetes_secrets_keyring
Version: 0.2.5
Summary: Keyring backend using Kubernetes secrets.
Author-email: Stan Hatko <stan_hatko@live.com>
Project-URL: Repository, https://github.com/StanHatko/kubernetes_secrets_backend
Classifier: Programming Language :: Python :: 3
Classifier: License :: OSI Approved :: MIT License
Classifier: Operating System :: POSIX :: Linux
Requires-Python: >=3.9
Requires-Dist: keyring >=25.0.0
